iothinkweld4/__init__.py
iothinkweld4/welding.py
iothinkweld4-1.0.1.dist-info/METADATA
iothinkweld4-1.0.1.dist-info/WHEEL
iothinkweld4-1.0.1.dist-info/licenses/LICENSE.txt
iothinkweld4-1.0.1.dist-info/RECORD
