Metadata-Version: 2.1
Name: iothinkweld4
Version: 1.0.1
Summary: A function to calculate standard line
Author-email: chenxiahang <hdecnu@163.com>
License-File: LICENSE.txt
Classifier: License :: OSI Approved :: MIT License
Classifier: Operating System :: OS Independent
Classifier: Programming Language :: Python :: 3
